bars.py
bars-0.0.1.dist-info/DESCRIPTION.rst
bars-0.0.1.dist-info/METADATA
bars-0.0.1.dist-info/RECORD
bars-0.0.1.dist-info/WHEEL
bars-0.0.1.dist-info/entry_points.txt
bars-0.0.1.dist-info/metadata.json
bars-0.0.1.dist-info/top_level.txt
