Metadata-Version: 2.0
Name: bars
Version: 0.0.1
Summary: A command-line interface that loads a CSV file and outputs a bar chart.
Home-page: https://github.com/flother/bars
Author: UNKNOWN
Author-email: UNKNOWN
License: UNKNOWN
Platform: UNKNOWN
Classifier: Development Status :: 4 - Beta
Classifier: Environment :: Console
Classifier: Intended Audience :: Developers
Classifier: Intended Audience :: Science/Research
Classifier: Intended Audience :: System Administrators
Classifier: License :: OSI Approved :: MIT License
Classifier: Natural Language :: English
Classifier: Programming Language :: Python :: 3
Classifier: Topic :: Utilities
Requires-Dist: agate (==1.3.1)
Requires-Dist: click (==6.6)
